setuptools_npm.py
setuptools_npm-0.3.dist-info/LICENSE
setuptools_npm-0.3.dist-info/METADATA
setuptools_npm-0.3.dist-info/WHEEL
setuptools_npm-0.3.dist-info/entry_points.txt
setuptools_npm-0.3.dist-info/top_level.txt
setuptools_npm-0.3.dist-info/RECORD
