Metadata-Version: 2.1
Name: setuptools-npm
Version: 0.3
Summary: Plugin for setuptools and npm
Home-page: https://github.com/CZ-NIC/setuptools-npm
Author: Jan Musílek
Author-email: jan.musilek@nic.cz
License: GPLv3+
Classifier: Development Status :: 3 - Alpha
Classifier: Intended Audience :: Developers
Classifier: License :: OSI Approved :: GNU General Public License v3 or later (GPLv3+)
Classifier: Operating System :: OS Independent
Classifier: Programming Language :: Python
Classifier: Programming Language :: Python :: 3.7
Classifier: Programming Language :: Python :: 3.8
Classifier: Programming Language :: Python :: 3.9
Classifier: Programming Language :: Python :: 3.10
Classifier: Topic :: Software Development :: Build Tools
Requires-Python: ~=3.7
License-File: LICENSE
Provides-Extra: quality
Requires-Dist: doc8 ; extra == 'quality'
Requires-Dist: flake8 ; extra == 'quality'
Requires-Dist: isort ; extra == 'quality'
